examples/__init__.py
examples/unit_test_formulas/__init__.py
examples/unit_test_formulas/growing_degrees_day.py
examples/unit_test_formulas/unit_testing_formulas_in_Excel.py
examples/unit_test_formulas/unit_testing_formulas_in_Python.py
flyingkoala/__init__.py
flyingkoala/flyingkoala.py
flyingkoala/accounting/__init__.py
flyingkoala/accounting/harvest.py
flyingkoala/accounting/utils.py
flyingkoala/bom/__init__.py
flyingkoala/bom/bom.py
flyingkoala/database/MySQL.py
flyingkoala/database/__init__.py
flyingkoala/energy/__init__.py
flyingkoala/energy/energy.py
flyingkoala/horticulture/__init__.py
flyingkoala/horticulture/horticulture.py
flyingkoala/timeseries/__init__.py
flyingkoala/timeseries/timeseries.py
flyingkoala-0.0.10b2.dist-info/LICENSE
flyingkoala-0.0.10b2.dist-info/METADATA
flyingkoala-0.0.10b2.dist-info/WHEEL
flyingkoala-0.0.10b2.dist-info/top_level.txt
flyingkoala-0.0.10b2.dist-info/RECORD
