Metadata-Version: 2.1
Name: flyingkoala
Version: 0.0.10b2
Summary: Integration of xlwings and xlcalculator with MS Excel plug-in
Home-page: https://github.com/bradbase/flyingkoala
Author: Bradley van Ree
Author-email: flyingkoala@bradbase.net
License: UNKNOWN
Keywords: xls,excel,spreadsheet,workbook,vba,macro,data analysis,analysisreading excel,excel formula,excel formulas,excel equations,excel equation,formula,formulas,equation,equations,pandas,harvest,timeseries,time series,energy,accounting,horticulture,research,visualization,scenario analysis,modelling,model,unit testing,testing,audit
Platform: UNKNOWN
Classifier: Programming Language :: Python :: 3
Classifier: License :: OSI Approved :: GNU General Public License v3 (GPLv3)
Classifier: Operating System :: Microsoft :: Windows
Classifier: Operating System :: MacOS :: MacOS X
Requires-Dist: xlwings (>=0.15.8)
Requires-Dist: numpy (>=1.15.0)
Requires-Dist: pandas (>=0.25.0)
Requires-Dist: xlfunctions (<=0.0.3b0)
Requires-Dist: xlcalculator (<=0.0.5b0)
